defermi/__init__.py
defermi/analysis.py
defermi/defects.py
defermi/elasticity.py
defermi/electronic_structure.py
defermi/entries.py
defermi/generator.py
defermi/plotter.py
defermi/structure.py
defermi/thermodynamics.py
defermi/chempots/__init__.py
defermi/chempots/core.py
defermi/chempots/generator.py
defermi/chempots/oxygen.py
defermi/chempots/phase_diagram.py
defermi/chempots/reservoirs.py
defermi/cli/inputs.py
defermi/cli/main.py
defermi/corrections/__init__.py
defermi/corrections/freysoldt.py
defermi/corrections/kumagai.py
defermi/testing/__init__.py
defermi/testing/chempots.py
defermi/testing/core.py
defermi/testing/defects.py
defermi/testing/structure.py
defermi/tools/__init__.py
defermi/tools/materials_project.py
defermi/tools/structure.py
defermi/tools/utils.py
defermi-1.4.0.dist-info/METADATA
defermi-1.4.0.dist-info/WHEEL
defermi-1.4.0.dist-info/entry_points.txt
defermi-1.4.0.dist-info/top_level.txt
defermi-1.4.0.dist-info/RECORD
