Metadata-Version: 2.4
Name: defermi
Version: 1.4.0
Summary: Compute and analyse point-defect equilibria.
Author: Lorenzo Villa
Requires-Python: >=3.11
Requires-Dist: ase
Requires-Dist: pymatgen>=2023.3.23
Requires-Dist: pymatgen-analysis-defects>=2023.3.25
Requires-Dist: mp-api
Requires-Dist: streamlit>=1.51.0
Provides-Extra: test
Requires-Dist: pytest; extra == "test"
